Workbook

Sheet Assumptions
A1: Assumptions & Unit Prices — Azure West Europe (USD, list prices captured 11-Jun-2026)
A3: General
A4: Hours per month (Azure calculator convention) | B4: 730 | D4: Azure Pricing Calculator default
A5: Web server VM count (availability set) | B5: 2 | D5: Architecture definition: 2x web servers
A6: Compute — Standard_D2s_v5 (2 vCPU / 8 GiB), West Europe
A7: Linux/base compute rate, PAYG ($/hr) | B7: 0.115 | D7: Source: Azure VM list pricing via cloudprice.net, 11-Jun-2026 (East US = $0.096)
A8: Windows Server license component ($/hr) | B8: 0.092 | D8: Source: Azure Windows VM pricing, uplift over Linux for 2-vCPU sizes (waived by Azure Hybrid Benefit)
A9: 1-year Reserved Instance, compute ($/hr) | B9: 0.0679 | D9: Source: Azure reservation pricing, ~41% below PAYG compute; verify in calculator
A10: 3-year Reserved Instance, compute ($/hr) | B10: 0.0443 | D10: Source: Azure reservation pricing, ~61% below PAYG compute; verify in calculator
A11: OS disk per VM: P10 Premium SSD 128 GiB ($/mo) | B11: 21.68 | D11: Source: Azure Managed Disks pricing, West Europe (East US = $19.71)
A12: Networking
A13: Standard Load Balancer, first 5 rules ($/hr) | B13: 0.025 | D13: Source: Azure Load Balancer pricing page
A14: Load Balancer data processed ($/GB) | B14: 0.005 | D14: Source: Azure Load Balancer pricing page
A15: Load Balancer data processed per month (GB) | B15: 1536 | D15: Usage assumption: ~1.5 TB through LB (inbound + responses)
A16: Internet egress price, Europe ($/GB after free tier) | B16: 0.087 | D16: Source: Azure Bandwidth pricing, 100 GB-10 TB tier, Europe
A17: Free egress allowance (GB/mo) | B17: 100 | D17: Source: Azure Bandwidth pricing — first 100 GB/month free
A18: Estimated outbound internet traffic (GB/mo) | B18: 1024 | D18: Usage assumption per assignment: ~1 TB outbound
A19: Cache & Database
A20: Azure Cache for Redis, Standard C1 1 GiB ($/hr) | B20: 0.146 | D20: Source: Azure Cache pricing, West Europe (East US = $0.138/hr per cloudpricecheck.com, 11-Jun-2026)
A21: Azure SQL Database, Standard S2 50 DTU ($/hr) | B21: 0.1109 | D21: Source: Azure SQL single-database DTU pricing, West Europe; includes 250 GB storage (East US = $0.1009/hr)
A22: Storage — Blob (general purpose v2, Hot tier)
A23: Hot LRS capacity ($/GB-mo, first 50 TB) | B23: 0.0196 | D23: Source: Azure Blob Storage pricing, West Europe (nops.io Azure storage guide, 2026)
A24: Hot GRS capacity ($/GB-mo, first 50 TB) | B24: 0.0392 | D24: Source: Azure Blob Storage pricing, West Europe — GRS = 2x LRS
A25: Stored data (GB) | B25: 1024 | D25: Usage assumption: 1 TB of static assets/backups
A26: PaaS Comparison — Azure App Service Premium v3, West Europe
A27: P1v3 Windows (2 vCPU / 8 GiB) ($/mo per instance) | B27: 265 | D27: Source: Azure App Service Windows pricing (East US = ~$241/mo per pump.co guide, Dec-2025) + WE uplift
A28: P1v3 Linux (2 vCPU / 8 GiB) ($/mo per instance) | B28: 137 | D28: Source: Azure App Service Linux pricing (East US = ~$124/mo) + WE uplift
A29: App Service instance count | B29: 2 | D29: Like-for-like with 2 web VMs
A30: Regional Comparison Reference — East US
A31: D2s_v5 Linux compute, East US ($/hr) | B31: 0.096 | D31: Source: cloudprice.net / vantage.sh, 11-Jun-2026
A32: Blob Hot LRS, East US ($/GB-mo) | B32: 0.018 | D32: Source: Azure Blob Storage pricing
A34: Blue cells are inputs. Prices are point-in-time USD list prices and drift over time — refresh against https://azure.microsoft.com/pricing/calculator/ before relying on totals.

Sheet Cost Estimate
A1: Monthly Cost Estimate — 3-Tier Web Application, West Europe (Pay-As-You-Go baseline, USD)
A3: Service | B3: SKU / Tier | C3: Configuration | D3: Qty | E3: Unit price | F3: Monthly cost
A4: Virtual Machines (web tier) | B4: Standard_D2s_v5, Windows Server | C4: 2 vCPU / 8 GiB, availability set, 730 hrs | D4: =Assumptions!$B$5 -> 2 | E4: =(Assumptions!$B$7+Assumptions!$B$8)*Assumptions!$B$4 -> 151.11 | F4: =D4*E4 -> 302.22
A5: Managed Disks | B5: P10 Premium SSD, 128 GiB (LRS) | C5: OS disk, one per VM | D5: =Assumptions!$B$5 -> 2 | E5: =Assumptions!$B$11 -> 21.68 | F5: =D5*E5 -> 43.36
A6: Load Balancer | B6: Standard, regional | C6: <=5 rules + 1,536 GB data processed | D6: 1 | E6: =Assumptions!$B$13*Assumptions!$B$4+Assumptions!$B$14*Assumptions!$B$15 -> 25.93 | F6: =D6*E6 -> 25.93
A7: Azure Cache for Redis | B7: Standard C1 (1 GiB, replicated) | C7: Session/state cache, 730 hrs | D7: 1 | E7: =Assumptions!$B$20*Assumptions!$B$4 -> 106.58 | F7: =D7*E7 -> 106.58
A8: Azure SQL Database | B8: Single DB, Standard S2 (50 DTU) | C8: Includes 250 GB storage, 730 hrs | D8: 1 | E8: =Assumptions!$B$21*Assumptions!$B$4 -> 80.957 | F8: =D8*E8 -> 80.957
A9: Blob Storage | B9: GPv2, Hot, GRS | C9: 1,024 GB capacity (transactions excluded) | D9: 1 | E9: =Assumptions!$B$24*Assumptions!$B$25 -> 40.1408 | F9: =D9*E9 -> 40.1408
A10: Bandwidth | B10: Internet egress (Europe) | C10: 1,024 GB out, first 100 GB free | D10: 1 | E10: =(Assumptions!$B$18-Assumptions!$B$17)*Assumptions!$B$16 -> 80.388 | F10: =D10*E10 -> 80.388
A11: TOTAL — Pay-As-You-Go baseline | F11: =SUM(F4:F10) -> 679.5758
A13: Mirrors an Azure Pricing Calculator export. Green = pulls from Assumptions sheet. Excludes blob transaction/ops charges (<$2/mo at assumed volumes) and support plans.

Sheet Optimization Scenarios
A1: What-If Scenarios — Cost Optimization Analysis (USD/month)
A3: A. Billing model — 2x D2s_v5 Windows web VMs (compute + OS license)
A4: Option | B4: Cost/month | C4: Saving vs PAYG | D4: Saving % | E4: Notes
A5: Pay-As-You-Go | B5: =(Assumptions!$B$7+Assumptions!$B$8)*Assumptions!$B$4*Assumptions!$B$5 -> 302.22 | C5: =$B$5-B5 -> 0 | D5: =C5/$B$5 -> 0 | E5: Full flexibility, no commitment
A6: 1-year Reserved Instance | B6: =(Assumptions!$B$9+Assumptions!$B$8)*Assumptions!$B$4*Assumptions!$B$5 -> 233.454 | C6: =$B$5-B6 -> 68.766 | D6: =C6/$B$5 -> 0.22753623 | E6: Reservation covers compute only; Windows license still billed
A7: 3-year Reserved Instance | B7: =(Assumptions!$B$10+Assumptions!$B$8)*Assumptions!$B$4*Assumptions!$B$5 -> 198.998 | C7: =$B$5-B7 -> 103.222 | D7: =C7/$B$5 -> 0.34154589 | E7: Deepest compute discount, 3-year lock-in
A8: PAYG + Azure Hybrid Benefit | B8: =Assumptions!$B$7*Assumptions!$B$4*Assumptions!$B$5 -> 167.9 | C8: =$B$5-B8 -> 134.32 | D8: =C8/$B$5 -> 0.44444444 | E8: Existing Windows Server licenses with Software Assurance waive the license meter
A9: 3-year RI + Azure Hybrid Benefit | B9: =Assumptions!$B$10*Assumptions!$B$4*Assumptions!$B$5 -> 64.678 | C9: =$B$5-B9 -> 237.542 | D9: =C9/$B$5 -> 0.78599034 | E9: Stacked: reservation discount on compute + license waived
A11: B. Storage redundancy — 1,024 GB Blob, Hot tier
A12: Option | B12: Cost/month | C12: Delta vs GRS | D12: Delta % | E12: Notes
A13: GRS (geo-redundant, 6 copies across 2 regions) | B13: =Assumptions!$B$24*Assumptions!$B$25 -> 40.1408 | C13: 0 | D13: 0 | E13: Survives a full regional outage; baseline in the estimate
A14: LRS (locally redundant, 3 copies in 1 datacenter) | B14: =Assumptions!$B$23*Assumptions!$B$25 -> 20.0704 | C14: =B13-B14 -> 20.0704 | D14: =C14/B13 -> 0.5 | E14: Half the cost; acceptable for re-creatable static assets
A16: C. IaaS vs PaaS — web tier (2 VMs + disks + LB vs App Service P1v3 x2)
A17: Option | B17: Cost/month | C17: Delta vs IaaS | D17: Delta % | E17: Notes
A18: IaaS: 2x D2s_v5 Windows PAYG + 2x P10 disks + Std LB | B18: =(Assumptions!$B$7+Assumptions!$B$8)*Assumptions!$B$4*Assumptions!$B$5+Assumptions!$B$11*Assumptions!$B$5+Assumptions!$B$13*Assumptions!$B$4+Assumptions!$B$14*Assumptions!$B$15 -> 371.51 | E18: Self-managed: you patch the OS, configure the LB, manage scaling
A19: PaaS: App Service P1v3 Windows x2 | B19: =Assumptions!$B$27*Assumptions!$B$29 -> 530 | C19: =B18-B19 -> -158.49 | D19: =C19/B18 -> -0.42661032 | E19: Built-in LB, autoscale, patching, deployment slots — disks and LB line items disappear
A20: PaaS: App Service P1v3 Linux x2 | B20: =Assumptions!$B$28*Assumptions!$B$29 -> 274 | C20: =B18-B20 -> 97.51 | D20: =C20/B18 -> 0.26246938 | E20: Same platform benefits without the Windows license premium
A22: D. Regional price check — same SKUs, West Europe vs East US
A23: Item | B23: West Europe | C23: East US | D23: WE premium | E23: Notes
A24: D2s_v5 Linux compute ($/hr) | B24: =Assumptions!$B$7 -> 0.115 | C24: =Assumptions!$B$31 -> 0.096 | D24: =B24/C24-1 -> 0.19791667 | E24: General-purpose compute is ~20% dearer in West Europe
A25: Blob Hot LRS ($/GB-mo) | B25: =Assumptions!$B$23 -> 0.0196 | C25: =Assumptions!$B$32 -> 0.018 | D25: =B25/C25-1 -> 0.088888889 | E25: Storage premium is smaller (~9%)
A27: E. Fully optimized architecture vs baseline
A28: Scenario | B28: Cost/month | C28: Saving | D28: Saving % | E28: Levers applied
A29: Baseline: PAYG Windows VMs + GRS blob | B29: ='Cost Estimate'!$F$11 -> 679.5758 | E29: As per Cost Estimate sheet
A30: Optimized: 3-yr RI + Hybrid Benefit + LRS blob | B30: =Assumptions!$B$10*Assumptions!$B$4*Assumptions!$B$5+Assumptions!$B$11*Assumptions!$B$5+Assumptions!$B$13*Assumptions!$B$4+Assumptions!$B$14*Assumptions!$B$15+Assumptions!$B$20*Assumptions!$B$4+Assumptions!$B$21*Assumptions!$B$4+Assumptions!$B$23*Assumptions!$B$25+(Assumptions!$B$18-Assumptions!$B$17)*Assumptions!$B$16 -> 421.9634 | C30: =B29-B30 -> 257.6124 | D30: =C30/B29 -> 0.37907824 | E30: Reservation + existing licenses + right-sized redundancy
